tg_msg_forwarder/__init__.py
tg_msg_forwarder/actions.py
tg_msg_forwarder/db.py
tg_msg_forwarder/main.py
tg_msg_forwarder-0.1.0.dist-info/licenses/LICENSE
tg_msg_forwarder-0.1.0.dist-info/METADATA
tg_msg_forwarder-0.1.0.dist-info/WHEEL
tg_msg_forwarder-0.1.0.dist-info/entry_points.txt
tg_msg_forwarder-0.1.0.dist-info/top_level.txt
tg_msg_forwarder-0.1.0.dist-info/RECORD
