Metadata-Version: 2.4
Name: tg-msg-forwarder
Version: 0.1.0
Summary: 一个高度可配置的工具，用于实时监听Telegram消息并转发到钉钉、飞书、Slack或数据库。
Author-email: Your Name <you@example.com>
License: MIT License
Project-URL: Homepage, https://github.com/yourusername/tg-msg-forwarder
Project-URL: Bug Tracker, https://github.com/yourusername/tg-msg-forwarder/issues
Classifier: Programming Language :: Python :: 3
Classifier: License :: OSI Approved :: MIT License
Classifier: Operating System :: OS Independent
Classifier: Topic :: Communications :: Chat
Classifier: Topic :: System :: Logging
Requires-Python: >=3.8
License-File: LICENSE
Requires-Dist: telethon
Requires-Dist: requests
Requires-Dist: sqlalchemy
Requires-Dist: PyMySQL
Requires-Dist: pysocks
Dynamic: license-file
